dataprep_tools/__init__.py
dataprep_tools/car_generators.py
dataprep_tools/car_splitters.py
dataprep_tools/commp_calculators.py
dataprep_tools/end_to_end.py
dataprep_tools/utils/__init__.py
dataprep_tools/utils/car_then_split.py
dataprep_tools-0.0.15.dist-info/METADATA
dataprep_tools-0.0.15.dist-info/WHEEL
dataprep_tools-0.0.15.dist-info/RECORD
