Metadata-Version: 2.1
Name: dataprep_tools
Version: 0.0.15
Summary: Utils to prepare data for filecoin deals
Author: Anjor
Classifier: Operating System :: OS Independent
Classifier: Programming Language :: Python :: 3
